{
  "_id": "b2SNtc9L6rPcCbmF",
  "name": "Basic Psychic Magic (UC) (1 pt)",
  "permission": {
    "default": 0
  },
  "type": "feat",
  "data": {
    "description": {
      "value": "<p><strong>Requirements:</strong>&nbsp;Aberrant subtype, Charisma 10.</p>\n<p>Select one spell from the following list:&nbsp;</p>\n<ul>\n<li>@Compendium[pf1.spells.zymaptg3vmnvfvxl]{Dancing Lights}</li>\n<li>@Compendium[pf1.spells.uqh87jz757r2cb7r]{Detect Magic}</li>\n<li>@Compendium[pf1.spells.mtxqp85izkb20djq]{Ghost Sound}</li>\n<li>@Compendium[pf1.spells.z3ysa1xxmzgj14sd]{Grave Words}</li>\n<li>@Compendium[pf1.spells.yssjgukwe3dgjhf3]{Know Direction}</li>\n<li>@Compendium[pf1.spells.99xovzg8h1nh9o9a]{Lullaby}</li>\n<li>@Compendium[pf1.spells.p8lm7khq3ynyif21]{Mage Hand}</li>\n<li>@Compendium[pf1.spells.ug7ycubjoxgp7ppc]{Open/Close}</li>\n<li>@Compendium[pf1.spells.f6k11j4pvmkka4e9]{Telekinetic Projectile}</li>\n</ul>\n<p>The eidolon can cast that spell as a psychic spell at will. The spell requires thought and emotion components as normal for psychic magic (Pathfinder RPG Occult Adventures&nbsp;144).</p>\n<p>The eidolon’s caster level is equal to the eidolon’s Hit Dice – 2 (minimum CL 1st). The save DC equals 10 + 1/2 the eidolon’s HD + the eidolon’s Charisma modifier. This evolution can be selected more than once, selecting a different spell each time.</p>",
      "chat": "",
      "unidentified": ""
    },
    "tags": [],
    "activation": {
      "cost": 1,
      "type": ""
    },
    "unchainedAction": {
      "activation": {
        "cost": 1,
        "type": ""
      }
    },
    "duration": {
      "value": null,
      "units": ""
    },
    "target": {
      "value": ""
    },
    "range": {
      "value": null,
      "units": "",
      "maxIncrements": 1,
      "minValue": null,
      "minUnits": "",
      "long": null
    },
    "uses": {
      "value": 0,
      "max": 0,
      "per": null,
      "autoDeductCharges": true,
      "autoDeductChargesCost": "1"
    },
    "measureTemplate": {
      "type": "",
      "size": "",
      "overrideColor": false,
      "customColor": "",
      "overrideTexture": false,
      "customTexture": ""
    },
    "attackName": "",
    "actionType": "",
    "attackBonus": "",
    "critConfirmBonus": "",
    "damage": {
      "parts": [],
      "critParts": [],
      "nonCritParts": []
    },
    "attackParts": [],
    "formulaicAttacks": {
      "count": {
        "formula": "",
        "value": null
      },
      "bonus": {
        "formula": ""
      },
      "label": null
    },
    "formula": "",
    "ability": {
      "attack": null,
      "damage": null,
      "damageMult": 1,
      "critRange": 20,
      "critMult": 2
    },
    "save": {
      "dc": 0,
      "type": "",
      "description": ""
    },
    "effectNotes": "",
    "attackNotes": "",
    "soundEffect": "",
    "changes": [],
    "changeFlags": {
      "loseDexToAC": false,
      "noEncumbrance": false,
      "mediumArmorFullSpeed": false,
      "heavyArmorFullSpeed": false,
      "noStr": false,
      "noDex": false,
      "oneInt": false,
      "oneWis": false,
      "oneCha": false
    },
    "contextNotes": [],
    "links": {
      "children": [],
      "charges": []
    },
    "tag": "",
    "useCustomTag": false,
    "armorProf": {
      "value": [],
      "custom": ""
    },
    "weaponProf": {
      "value": [],
      "custom": ""
    },
    "flags": {
      "boolean": [],
      "dictionary": []
    },
    "featType": "classFeat",
    "associations": {
      "classes": [
        [
          "Eidolon (Unchained)"
        ]
      ]
    },
    "showInQuickbar": false,
    "nonlethal": false,
    "abilityType": "none",
    "crOffset": "",
    "disabled": false,
    "attack": {
      "parts": []
    }
  },
  "flags": {},
  "img": "systems/pf1/icons/skills/blue_26.jpg",
  "effects": []
}