{
  "_id": "BO7BEFHDcf6qBaYV",
  "name": "Combat Style Feat",
  "permission": {
    "default": 0
  },
  "type": "feat",
  "data": {
    "description": {
      "value": "<p>At 2nd level, a ranger must select one&nbsp;<a href=\"https://www.d20pfsrd.com/classes/core-classes/ranger/ranger-combat-styles/\">combat style</a>&nbsp;to pursue.</p>\n<p>The ranger’s expertise manifests in the form of bonus feats at 2nd, 6th, 10th, 14th, and 18th level. He can choose feats from his selected combat style, even if he does not have the normal prerequisites.</p>\n<p>The benefits of the ranger’s chosen style feats apply&nbsp;only&nbsp;when he wears light, medium, or no armor. He loses all benefits of his combat style feats when wearing heavy armor. Once a ranger selects a combat style, it cannot be changed.</p>",
      "chat": "",
      "unidentified": ""
    },
    "tags": [],
    "activation": {
      "cost": 1,
      "type": "passive"
    },
    "unchainedAction": {
      "activation": {
        "cost": 1,
        "type": "passive"
      }
    },
    "duration": {
      "value": null,
      "units": ""
    },
    "target": {
      "value": ""
    },
    "range": {
      "value": null,
      "units": "",
      "maxIncrements": 1,
      "minValue": null,
      "minUnits": "",
      "long": null
    },
    "uses": {
      "value": 0,
      "max": 0,
      "per": "",
      "autoDeductCharges": true,
      "autoDeductChargesCost": "1"
    },
    "measureTemplate": {
      "type": "",
      "size": "0",
      "overrideColor": false,
      "customColor": "",
      "overrideTexture": false,
      "customTexture": ""
    },
    "attackName": "",
    "actionType": "",
    "attackBonus": "",
    "critConfirmBonus": "",
    "damage": {
      "parts": [],
      "critParts": [],
      "nonCritParts": []
    },
    "attackParts": [],
    "formulaicAttacks": {
      "count": {
        "formula": "",
        "value": null
      },
      "bonus": {
        "formula": ""
      },
      "label": null
    },
    "formula": "",
    "ability": {
      "attack": null,
      "damage": null,
      "damageMult": 1,
      "critRange": 20,
      "critMult": 2
    },
    "save": {
      "dc": 0,
      "type": "",
      "description": ""
    },
    "effectNotes": "",
    "attackNotes": "",
    "soundEffect": "",
    "changes": [
      {
        "_id": "mac5t9bg",
        "formula": "floor((@classes.ranger.level + 2) / 4)",
        "operator": "add",
        "subTarget": "bonusFeats",
        "modifier": "untyped",
        "priority": 0,
        "value": 0,
        "target": "misc"
      }
    ],
    "changeFlags": {
      "loseDexToAC": false,
      "noEncumbrance": false,
      "mediumArmorFullSpeed": false,
      "heavyArmorFullSpeed": false,
      "noStr": false,
      "noDex": false,
      "oneInt": false,
      "oneWis": false,
      "oneCha": false
    },
    "contextNotes": [],
    "links": {
      "children": [],
      "charges": []
    },
    "tag": "",
    "useCustomTag": false,
    "armorProf": {
      "value": [],
      "custom": ""
    },
    "weaponProf": {
      "value": [],
      "custom": ""
    },
    "flags": {
      "boolean": [],
      "dictionary": []
    },
    "featType": "classFeat",
    "associations": {
      "classes": [
        [
          "Ranger"
        ]
      ]
    },
    "showInQuickbar": false,
    "nonlethal": false,
    "abilityType": "ex",
    "crOffset": "",
    "disabled": false,
    "attack": {
      "parts": []
    }
  },
  "flags": {},
  "img": "systems/pf1/icons/feats/double-slice.jpg",
  "effects": []
}