{
  "_id": "FDCBEgVbfJ5uid3f",
  "name": "Momentary Glimpse",
  "permission": {
    "default": 0
  },
  "type": "feat",
  "data": {
    "description": {
      "value": "<p>Once per day, you can gain a glimpse into your immediate future. On the round after you use this ability, you gain a +2 insight bonus on a single attack roll, saving throw, or skill check or to your Armor Class until the start of your next turn.</p>\n<p>At 5th level, and every four levels thereafter, you can use this ability one additional time per day.</p>",
      "chat": "",
      "unidentified": ""
    },
    "tags": [],
    "activation": {
      "cost": 1,
      "type": "immediate"
    },
    "unchainedAction": {
      "activation": {
        "cost": 1,
        "type": "reaction"
      }
    },
    "duration": {
      "value": "1",
      "units": "round"
    },
    "target": {
      "value": "self"
    },
    "range": {
      "value": null,
      "units": "personal",
      "maxIncrements": 1,
      "minValue": null,
      "minUnits": "",
      "long": null
    },
    "uses": {
      "value": 0,
      "max": 0,
      "per": "day",
      "autoDeductCharges": true,
      "autoDeductChargesCost": "1",
      "maxFormula": "1 + floor((@classes.oracle.level - 1) / 4)"
    },
    "measureTemplate": {
      "type": "",
      "size": "",
      "overrideColor": false,
      "customColor": "",
      "overrideTexture": false,
      "customTexture": ""
    },
    "attackName": "",
    "actionType": "",
    "attackBonus": "",
    "critConfirmBonus": "",
    "damage": {
      "parts": [],
      "critParts": [],
      "nonCritParts": []
    },
    "attackParts": [],
    "formulaicAttacks": {
      "count": {
        "formula": "",
        "value": null
      },
      "bonus": {
        "formula": ""
      },
      "label": null
    },
    "formula": "",
    "ability": {
      "attack": null,
      "damage": null,
      "damageMult": 1,
      "critRange": 20,
      "critMult": 2
    },
    "save": {
      "dc": 0,
      "type": "",
      "description": ""
    },
    "effectNotes": "",
    "attackNotes": "",
    "soundEffect": "",
    "changes": [],
    "changeFlags": {
      "loseDexToAC": false,
      "noEncumbrance": false,
      "mediumArmorFullSpeed": false,
      "heavyArmorFullSpeed": false,
      "noStr": false,
      "noDex": false,
      "oneInt": false,
      "oneWis": false,
      "oneCha": false
    },
    "contextNotes": [],
    "links": {
      "children": [],
      "charges": []
    },
    "tag": "",
    "useCustomTag": false,
    "armorProf": {
      "value": [],
      "custom": ""
    },
    "weaponProf": {
      "value": [],
      "custom": ""
    },
    "flags": {
      "boolean": [],
      "dictionary": []
    },
    "featType": "classFeat",
    "associations": {
      "classes": [
        [
          "Oracle"
        ]
      ]
    },
    "showInQuickbar": false,
    "nonlethal": false,
    "abilityType": "su",
    "crOffset": "",
    "disabled": false,
    "attack": {
      "parts": []
    }
  },
  "flags": {},
  "img": "systems/pf1/icons/spells/light-royal-1.jpg",
  "effects": []
}