{
  "_id": "cMesEsnPGVXLnOxW",
  "name": "Vampiric Heart",
  "permission": {
    "default": 0
  },
  "type": "feat",
  "data": {
    "description": {
      "value": "<p>The vampire hunter gains&nbsp;<a href=\"https://www.d20pfsrd.com/gamemastering/special-abilities#TOC-Energy-Resistance\">energy resistance</a>&nbsp;equal to half his level against cold and electricity. Additionally, the vampire hunter’s heartbeat is undetectable. Any ability that detects or identifies the living, such as the&nbsp;<a href=\"https://www.d20pfsrd.com/bestiary/rules-for-monsters/universal-monster-rules#TOC-Lifesense-Su-\">lifesense</a>&nbsp;ability, does not perceive him. At 16th level, once per day when reduced to 0 or fewer&nbsp;<a href=\"https://www.d20pfsrd.com/gamemastering/combat#TOC-Hit-Points\">hit points</a>&nbsp;while this focus is activated, the vampire hunter immediately turns gaseous (as the spell @Compendium[pf1.spells.mqdoexj35atgqafn]{Gaseous Form}) for up to a number of rounds equal to half his level and he gains a number of&nbsp;<a href=\"https://www.d20pfsrd.com/gamemastering/combat#TOC-Temporary-Hit-Points\">temporary hit points</a>&nbsp;equal to half his level. The vampire hunter can leave&nbsp;<a href=\"https://www.d20pfsrd.com/magic/all-spells/g/gaseous-form\">gaseous form</a>&nbsp;at any time without losing these&nbsp;<a href=\"https://www.d20pfsrd.com/gamemastering/combat#TOC-Temporary-Hit-Points\">temporary hit points</a>. This effect ends after these rounds have elapsed, after the vampire hunter loses the&nbsp;<a href=\"https://www.d20pfsrd.com/gamemastering/combat#TOC-Temporary-Hit-Points\">temporary hit points</a>, or once this focus is no longer active, at which point the vampire hunter immediately becomes corporeal and loses these&nbsp;<a href=\"https://www.d20pfsrd.com/gamemastering/combat#TOC-Temporary-Hit-Points\">temporary hit points</a>. If he has not received&nbsp;<a href=\"https://www.d20pfsrd.com/magic#TOC-Conjuration-Healing\">healing</a>&nbsp;in the interim, this returns the vampire hunter to the number of&nbsp;<a href=\"https://www.d20pfsrd.com/gamemastering/combat#TOC-Hit-Points\">hit points</a>&nbsp;he had after the attack or effect that triggered this ability.</p>",
      "chat": "",
      "unidentified": ""
    },
    "tags": [],
    "activation": {
      "cost": 1,
      "type": ""
    },
    "unchainedAction": {
      "activation": {
        "cost": 1,
        "type": ""
      }
    },
    "duration": {
      "value": null,
      "units": ""
    },
    "target": {
      "value": ""
    },
    "range": {
      "value": null,
      "units": "",
      "maxIncrements": 1,
      "minValue": null,
      "minUnits": "",
      "long": null
    },
    "uses": {
      "value": 0,
      "max": 0,
      "per": null,
      "autoDeductCharges": true,
      "autoDeductChargesCost": "1"
    },
    "measureTemplate": {
      "type": "",
      "size": "0",
      "overrideColor": false,
      "customColor": "",
      "overrideTexture": false,
      "customTexture": ""
    },
    "attackName": "",
    "actionType": "",
    "attackBonus": "",
    "critConfirmBonus": "",
    "damage": {
      "parts": [],
      "critParts": [],
      "nonCritParts": []
    },
    "attackParts": [],
    "formulaicAttacks": {
      "count": {
        "formula": "",
        "value": null
      },
      "bonus": {
        "formula": ""
      },
      "label": null
    },
    "formula": "",
    "ability": {
      "attack": null,
      "damage": null,
      "damageMult": 1,
      "critRange": 20,
      "critMult": 2
    },
    "save": {
      "dc": 0,
      "type": "",
      "description": ""
    },
    "effectNotes": "",
    "attackNotes": "",
    "soundEffect": "",
    "changes": [],
    "changeFlags": {
      "loseDexToAC": false,
      "noEncumbrance": false,
      "mediumArmorFullSpeed": false,
      "heavyArmorFullSpeed": false,
      "noStr": false,
      "noDex": false,
      "oneInt": false,
      "oneWis": false,
      "oneCha": false
    },
    "contextNotes": [],
    "links": {
      "children": [],
      "charges": []
    },
    "tag": "",
    "useCustomTag": false,
    "armorProf": {
      "value": [],
      "custom": ""
    },
    "weaponProf": {
      "value": [],
      "custom": ""
    },
    "flags": {
      "boolean": [],
      "dictionary": []
    },
    "featType": "classFeat",
    "associations": {
      "classes": [
        [
          "Vampire Hunter"
        ]
      ]
    },
    "showInQuickbar": false,
    "nonlethal": false,
    "abilityType": "su",
    "crOffset": "",
    "disabled": false,
    "attack": {
      "parts": []
    }
  },
  "flags": {},
  "img": "systems/pf1/icons/skills/beast_02.jpg",
  "effects": []
}