{
  "_id": "4y42ffrppap34t4i",
  "name": "Blade of Light",
  "permission": {
    "default": 0
  },
  "type": "spell",
  "data": {
    "description": {
      "value": "<div class=\"spell-description\">\n  <p>\n    <strong>School</strong>&nbsp;transmutation&nbsp;[good];\n    <strong>Level</strong>&nbsp;cleric/oracle 4, inquisitor 4, paladin 4;\n    \n    \n    \n    \n  </p>\n  <p>\n    <strong>Casting Time</strong>&nbsp;1 standard action<br>\n    <strong>Components</strong>&nbsp;V, S<br>\n  </p>\n  <p>\n    <strong>Range</strong>&nbsp;touch<br>\n    \n    <strong>Targets</strong>&nbsp;one melee weapon<br>\n    \n    <strong>Duration</strong>&nbsp;1 round/level<br>\n    <strong>Saving Throw</strong>&nbsp;none;&nbsp;<strong>Spell Resistance</strong>&nbsp;no<br>\n  </p>\n  <h2>Description</h2>\n  <p>This spell infuses a weapon with pure sunlight (the weapon need not be a bladed weapon). A weapon enhanced by this spell sheds light as if <i>daylight</i> had been cast on it. It functions as a magic and good weapon for the purposes of overcoming damage reduction. The weapon grants a +2 sacred bonus on attack rolls against undead and deals +1d6 points of damage on a successful hit against such foes; against incorporeal undead, it functions as if it had the <i>ghost touch</i> weapon special ability. The weapon automatically confirms critical hits against foes that are vulnerable to sunlight.</p>\n</div>\n",
      "chat": "",
      "unidentified": ""
    },
    "tags": [],
    "activation": {
      "cost": 1,
      "type": "standard"
    },
    "unchainedAction": {
      "activation": {
        "cost": 2,
        "type": "action"
      }
    },
    "duration": {
      "value": null,
      "units": ""
    },
    "target": {
      "value": "one melee weapon"
    },
    "range": {
      "value": null,
      "units": "touch",
      "maxIncrements": 1,
      "minValue": null,
      "minUnits": ""
    },
    "uses": {
      "value": 0,
      "max": 0,
      "per": "",
      "autoDeductCharges": true,
      "autoDeductChargesCost": "1"
    },
    "measureTemplate": {
      "type": "",
      "size": "0",
      "overrideColor": false,
      "customColor": "",
      "overrideTexture": false,
      "customTexture": ""
    },
    "attackName": "",
    "actionType": "",
    "attackBonus": "",
    "critConfirmBonus": "",
    "damage": {
      "parts": [],
      "critParts": [],
      "nonCritParts": []
    },
    "attackParts": [],
    "formulaicAttacks": {
      "count": {
        "formula": "",
        "value": null
      },
      "bonus": {
        "formula": ""
      },
      "label": null
    },
    "formula": "",
    "ability": {
      "attack": "",
      "damage": "",
      "damageMult": 1,
      "critRange": 20,
      "critMult": 2
    },
    "save": {
      "dc": "0",
      "type": "",
      "description": ""
    },
    "effectNotes": "",
    "attackNotes": "",
    "soundEffect": "",
    "links": {
      "children": []
    },
    "flags": {
      "boolean": [],
      "dictionary": []
    },
    "learnedAt": {
      "class": [
        [
          "cleric/oracle",
          4
        ],
        [
          "paladin",
          4
        ],
        [
          "inquisitor",
          4
        ]
      ],
      "domain": [],
      "subDomain": [],
      "elementalSchool": [],
      "bloodline": []
    },
    "level": 4,
    "clOffset": 0,
    "slOffset": 0,
    "school": "trs",
    "subschool": "",
    "types": "good",
    "nonlethal": false,
    "conditionals": [],
    "components": {
      "value": "",
      "verbal": true,
      "somatic": true,
      "material": false,
      "focus": false,
      "divineFocus": 0
    },
    "castTime": "",
    "materials": {
      "value": "",
      "focus": "",
      "gpValue": 0
    },
    "spellbook": "primary",
    "preparation": {
      "preparedAmount": 0,
      "maxAmount": 0,
      "autoDeductCharges": true,
      "spontaneousPrepared": true,
      "mode": "prepared"
    },
    "atWill": false,
    "sr": false,
    "shortDescription": "<p>This spell infuses a weapon with pure sunlight (the weapon need not be a bladed weapon). A weapon enhanced by this spell sheds light as if <i>daylight</i> had been cast on it. It functions as a magic and good weapon for the purposes of overcoming damage reduction. The weapon grants a +2 sacred bonus on attack rolls against undead and deals +1d6 points of damage on a successful hit against such foes; against incorporeal undead, it functions as if it had the <i>ghost touch</i> weapon special ability. The weapon automatically confirms critical hits against foes that are vulnerable to sunlight.</p>",
    "spellDuration": "1 round/level",
    "spellEffect": "",
    "spellArea": "",
    "showInQuickbar": false,
    "spellPoints": {
      "cost": "1 + @sl"
    },
    "domain": false,
    "slotCost": 1
  },
  "flags": {},
  "img": "systems/pf1/icons/misc/magic-swirl.png",
  "effects": []
}