{
  "_id": "o6vh3lrmi1hsdzmm",
  "name": "Instant Summons",
  "permission": {
    "default": 0
  },
  "type": "spell",
  "data": {
    "description": {
      "value": "<div class=\"spell-description\">\n  <p>\n    <strong>School</strong>&nbsp;conjuration&nbsp;(summoning);\n    <strong>Level</strong>&nbsp;psychic 7, sorcerer/wizard 7, witch 7;\n    <strong>Domain</strong>&nbsp;Rune 7;\n    \n    \n    \n  </p>\n  <p>\n    <strong>Casting Time</strong>&nbsp;1 standard action<br>\n    <strong>Components</strong>&nbsp;V, S, M (sapphire worth 1,000 gp)<br>\n  </p>\n  <p>\n    \n    \n    <strong>Targets</strong>&nbsp;one object weighing 10 lbs. or less whose longest dimension is 6 ft. or less<br>\n    \n    <strong>Duration</strong>&nbsp;permanent until discharged<br>\n      <strong>Saving Throw</strong>&nbsp;none;&nbsp;\n      <strong>Spell Resistance</strong>&nbsp;no<br>\n  </p>\n  <h2>Description</h2>\n  <p>You call some nonliving item directly to your hand from virtually any location.</p><p>First, you must place your <i>arcane mark</i> on the item. Then you cast this spell, which magically and invisibly inscribes the name of the item on a sapphire worth at least 1,000 gp. Thereafter, you can summon the item by speaking a special word (set by you when the spell is cast) and crushing the gem. The item appears instantly in your hand. Only you can use the gem in this way.</p><p>If the item is in the possession of another creature, the spell does not work, but you know who the possessor is and roughly where that creature is located when the summons occurs.</p><p>The inscription on the gem is invisible. It is also unreadable, except by means of a <i>read magic</i> spell, to anyone but you.</p><p>The item can be summoned from another plane, but only if no other creature has claimed ownership of it.</p>\n</div>\n",
      "chat": "",
      "unidentified": ""
    },
    "tags": [],
    "activation": {
      "cost": 1,
      "type": "standard"
    },
    "unchainedAction": {
      "activation": {
        "cost": 2,
        "type": "action"
      }
    },
    "duration": {
      "value": null,
      "units": ""
    },
    "target": {
      "value": "one object weighing 10 lbs. or less whose longest dimension is 6 ft. or less"
    },
    "range": {
      "value": null,
      "units": "",
      "maxIncrements": 1,
      "minValue": null,
      "minUnits": ""
    },
    "uses": {
      "value": 0,
      "max": 0,
      "per": "",
      "autoDeductCharges": true,
      "autoDeductChargesCost": "1"
    },
    "measureTemplate": {
      "type": "",
      "size": "0",
      "overrideColor": false,
      "customColor": "",
      "overrideTexture": false,
      "customTexture": ""
    },
    "attackName": "",
    "actionType": "",
    "attackBonus": "",
    "critConfirmBonus": "",
    "damage": {
      "parts": [],
      "critParts": [],
      "nonCritParts": []
    },
    "attackParts": [],
    "formulaicAttacks": {
      "count": {
        "formula": "",
        "value": null
      },
      "bonus": {
        "formula": ""
      },
      "label": null
    },
    "formula": "",
    "ability": {
      "attack": "",
      "damage": "",
      "damageMult": 1,
      "critRange": 20,
      "critMult": 2
    },
    "save": {
      "dc": "0",
      "type": "",
      "description": ""
    },
    "effectNotes": "",
    "attackNotes": "",
    "soundEffect": "",
    "links": {
      "children": []
    },
    "flags": {
      "boolean": [],
      "dictionary": []
    },
    "learnedAt": {
      "class": [
        [
          "sorcerer/wizard",
          7
        ],
        [
          "witch",
          7
        ],
        [
          "psychic",
          7
        ]
      ],
      "domain": [
        [
          "Rune",
          7
        ]
      ],
      "subDomain": [],
      "elementalSchool": [],
      "bloodline": []
    },
    "level": 7,
    "clOffset": 0,
    "slOffset": 0,
    "school": "con",
    "subschool": "summoning",
    "types": "",
    "nonlethal": false,
    "conditionals": [],
    "components": {
      "value": "",
      "verbal": true,
      "somatic": true,
      "material": true,
      "focus": false,
      "divineFocus": 0
    },
    "castTime": "",
    "materials": {
      "value": "sapphire worth 1,000 gp",
      "focus": "",
      "gpValue": 1000
    },
    "spellbook": "",
    "preparation": {
      "preparedAmount": 0,
      "maxAmount": 0,
      "autoDeductCharges": false,
      "spontaneousPrepared": false,
      "mode": "prepared"
    },
    "atWill": false,
    "sr": false,
    "shortDescription": "<p>You call some nonliving item directly to your hand from virtually any location.</p><p>First, you must place your <i>arcane mark</i> on the item. Then you cast this spell, which magically and invisibly inscribes the name of the item on a sapphire worth at least 1,000 gp. Thereafter, you can summon the item by speaking a special word (set by you when the spell is cast) and crushing the gem. The item appears instantly in your hand. Only you can use the gem in this way.</p><p>If the item is in the possession of another creature, the spell does not work, but you know who the possessor is and roughly where that creature is located when the summons occurs.</p><p>The inscription on the gem is invisible. It is also unreadable, except by means of a <i>read magic</i> spell, to anyone but you.</p><p>The item can be summoned from another plane, but only if no other creature has claimed ownership of it.</p>",
    "spellDuration": "permanent until discharged",
    "spellEffect": "",
    "spellArea": "",
    "showInQuickbar": false,
    "spellPoints": {
      "cost": ""
    },
    "domain": false,
    "slotCost": 1
  },
  "flags": {},
  "img": "systems/pf1/icons/misc/magic-swirl.png",
  "effects": []
}