{
  "_id": "tcwvpz002zmq61kw",
  "name": "Quell Energy",
  "permission": {
    "default": 0
  },
  "type": "spell",
  "data": {
    "description": {
      "value": "<div class=\"spell-description\">\n  <p>\n    <strong>School</strong>&nbsp;abjuration;\n    <strong>Level</strong>&nbsp;druid 3, hunter 3, inquisitor 3, occultist 3, psychic 3, shaman 3, sorcerer/wizard 3, witch 3;\n    \n    \n    \n    \n  </p>\n  <p>\n    <strong>Casting Time</strong>&nbsp;1 standard action<br>\n    <strong>Components</strong>&nbsp;V, S<br>\n  </p>\n  <p>\n    <strong>Range</strong>&nbsp;close (25 ft. + 5 ft./2 levels)<br>\n    \n    <strong>Targets</strong>&nbsp;one creature<br>\n    \n    <strong>Duration</strong>&nbsp;1 round/level<br>\n    <strong>Saving Throw</strong>&nbsp;Will partial;&nbsp;<strong>Spell Resistance</strong>&nbsp;yes<br>\n  </p>\n  <h2>Description</h2>\n  <p>You reduce the target creature's ability to tap into a single energy type (acid, cold, electricity, fire, or sonic) of your choice. This reduces damage of the selected type the creature deals with spells, spell-like abilities, and supernatural abilities by 10 points. Multiple castings of this spell stack. Damage from sources other than the creature, such as objects and magic items, is not reduced. If the damage of one of the creature's effects is negated entirely, any additional effects associated with that damage (such being stunned by <i>sound burst</i> o r set on fi re by a fi re e lemental) a re also negated. At 13th level, you reduce the target's damage by 20 points, and at 19th level, you reduce the target's damage by 30 points.  If the target succeeds on its saving throw, the spell's duration is reduced to 1 round.</p>\n</div>\n",
      "chat": "",
      "unidentified": ""
    },
    "tags": [],
    "activation": {
      "cost": 1,
      "type": "standard"
    },
    "unchainedAction": {
      "activation": {
        "cost": 2,
        "type": "action"
      }
    },
    "duration": {
      "value": null,
      "units": ""
    },
    "target": {
      "value": "one creature"
    },
    "range": {
      "value": null,
      "units": "close",
      "maxIncrements": 1,
      "minValue": null,
      "minUnits": ""
    },
    "uses": {
      "value": 0,
      "max": 0,
      "per": "",
      "autoDeductCharges": true,
      "autoDeductChargesCost": "1"
    },
    "measureTemplate": {
      "type": "",
      "size": "0",
      "overrideColor": false,
      "customColor": "",
      "overrideTexture": false,
      "customTexture": ""
    },
    "attackName": "",
    "actionType": "spellsave",
    "attackBonus": "",
    "critConfirmBonus": "",
    "damage": {
      "parts": [],
      "critParts": [],
      "nonCritParts": []
    },
    "attackParts": [],
    "formulaicAttacks": {
      "count": {
        "formula": "",
        "value": null
      },
      "bonus": {
        "formula": ""
      },
      "label": null
    },
    "formula": "",
    "ability": {
      "attack": "",
      "damage": "",
      "damageMult": 1,
      "critRange": 20,
      "critMult": 2
    },
    "save": {
      "dc": "0",
      "type": "will",
      "description": "Will partial"
    },
    "effectNotes": "",
    "attackNotes": "",
    "soundEffect": "",
    "links": {
      "children": []
    },
    "flags": {
      "boolean": [],
      "dictionary": []
    },
    "learnedAt": {
      "class": [
        [
          "sorcerer/wizard",
          3
        ],
        [
          "druid",
          3
        ],
        [
          "witch",
          3
        ],
        [
          "inquisitor",
          3
        ],
        [
          "shaman",
          3
        ],
        [
          "psychic",
          3
        ],
        [
          "occultist",
          3
        ],
        [
          "hunter",
          3
        ]
      ],
      "domain": [],
      "subDomain": [],
      "elementalSchool": [],
      "bloodline": []
    },
    "level": 3,
    "clOffset": 0,
    "slOffset": 0,
    "school": "abj",
    "subschool": "",
    "types": "",
    "nonlethal": false,
    "conditionals": [],
    "components": {
      "value": "",
      "verbal": true,
      "somatic": true,
      "material": false,
      "focus": false,
      "divineFocus": 0
    },
    "castTime": "",
    "materials": {
      "value": "",
      "focus": "",
      "gpValue": 0
    },
    "spellbook": "primary",
    "preparation": {
      "preparedAmount": 0,
      "maxAmount": 0,
      "autoDeductCharges": true,
      "spontaneousPrepared": true,
      "mode": "prepared"
    },
    "atWill": false,
    "sr": true,
    "shortDescription": "<p>You reduce the target creature's ability to tap into a single energy type (acid, cold, electricity, fire, or sonic) of your choice. This reduces damage of the selected type the creature deals with spells, spell-like abilities, and supernatural abilities by 10 points. Multiple castings of this spell stack. Damage from sources other than the creature, such as objects and magic items, is not reduced. If the damage of one of the creature's effects is negated entirely, any additional effects associated with that damage (such being stunned by <i>sound burst</i> o r set on fi re by a fi re e lemental) a re also negated. At 13th level, you reduce the target's damage by 20 points, and at 19th level, you reduce the target's damage by 30 points.  If the target succeeds on its saving throw, the spell's duration is reduced to 1 round.</p>",
    "spellDuration": "1 round/level",
    "spellEffect": "",
    "spellArea": "",
    "showInQuickbar": false,
    "spellPoints": {
      "cost": "1 + @sl"
    },
    "domain": false,
    "slotCost": 1
  },
  "flags": {},
  "img": "systems/pf1/icons/misc/magic-swirl.png",
  "effects": []
}