{
  "_id": "oall7obl22ds5rfg",
  "name": "Rune of Durability",
  "permission": {
    "default": 0
  },
  "type": "spell",
  "data": {
    "description": {
      "value": "<div class=\"spell-description\">\n  <p>\n    <strong>School</strong>&nbsp;transmutation;\n    <strong>Level</strong>&nbsp;sorcerer/wizard 3;\n    \n    \n    \n    \n  </p>\n  <p>\n    <strong>Casting Time</strong>&nbsp;1 minute<br>\n    <strong>Components</strong>&nbsp;V, S, M (iron filings)<br>\n  </p>\n  <p>\n    <strong>Range</strong>&nbsp;touch<br>\n    \n    <strong>Targets</strong>&nbsp;weapon touched<br>\n    \n    <strong>Duration</strong>&nbsp;permanent<br>\n    <strong>Saving Throw</strong>&nbsp;none;&nbsp;<strong>Spell Resistance</strong>&nbsp;no<br>\n  </p>\n  <h2>Description</h2>\n  <p>You inscribe an angular rune upon the surface of a weapon, increasing its hit points. A weapon that bears this rune multiplies its hit points by 2, as if it were one size category larger than it actually is. Placing more than one rune of this type on a weapon has no effect.</p>\n</div>\n",
      "chat": "",
      "unidentified": ""
    },
    "tags": [],
    "activation": {
      "cost": 1,
      "type": "minute"
    },
    "unchainedAction": {
      "activation": {
        "cost": 1,
        "type": "minute"
      }
    },
    "duration": {
      "value": null,
      "units": ""
    },
    "target": {
      "value": "weapon touched"
    },
    "range": {
      "value": null,
      "units": "touch",
      "maxIncrements": 1,
      "minValue": null,
      "minUnits": ""
    },
    "uses": {
      "value": 0,
      "max": 0,
      "per": "",
      "autoDeductCharges": true,
      "autoDeductChargesCost": "1"
    },
    "measureTemplate": {
      "type": "",
      "size": "0",
      "overrideColor": false,
      "customColor": "",
      "overrideTexture": false,
      "customTexture": ""
    },
    "attackName": "",
    "actionType": "",
    "attackBonus": "",
    "critConfirmBonus": "",
    "damage": {
      "parts": [],
      "critParts": [],
      "nonCritParts": []
    },
    "attackParts": [],
    "formulaicAttacks": {
      "count": {
        "formula": "",
        "value": null
      },
      "bonus": {
        "formula": ""
      },
      "label": null
    },
    "formula": "",
    "ability": {
      "attack": "",
      "damage": "",
      "damageMult": 1,
      "critRange": 20,
      "critMult": 2
    },
    "save": {
      "dc": "0",
      "type": "",
      "description": ""
    },
    "effectNotes": "",
    "attackNotes": "",
    "soundEffect": "",
    "links": {
      "children": []
    },
    "flags": {
      "boolean": [],
      "dictionary": []
    },
    "learnedAt": {
      "class": [
        [
          "sorcerer/wizard",
          3
        ]
      ],
      "domain": [],
      "subDomain": [],
      "elementalSchool": [],
      "bloodline": []
    },
    "level": 3,
    "clOffset": 0,
    "slOffset": 0,
    "school": "trs",
    "subschool": "",
    "types": "",
    "nonlethal": false,
    "conditionals": [],
    "components": {
      "value": "",
      "verbal": true,
      "somatic": true,
      "material": true,
      "focus": false,
      "divineFocus": 0
    },
    "castTime": "",
    "materials": {
      "value": "iron filings",
      "focus": "",
      "gpValue": 0
    },
    "spellbook": "primary",
    "preparation": {
      "preparedAmount": 0,
      "maxAmount": 0,
      "autoDeductCharges": true,
      "spontaneousPrepared": true,
      "mode": "prepared"
    },
    "atWill": false,
    "sr": false,
    "shortDescription": "<p>You inscribe an angular rune upon the surface of a weapon, increasing its hit points. A weapon that bears this rune multiplies its hit points by 2, as if it were one size category larger than it actually is. Placing more than one rune of this type on a weapon has no effect.</p>",
    "spellDuration": "permanent",
    "spellEffect": "",
    "spellArea": "",
    "showInQuickbar": false,
    "spellPoints": {
      "cost": "1 + @sl"
    },
    "domain": false,
    "slotCost": 1
  },
  "flags": {},
  "img": "systems/pf1/icons/misc/magic-swirl.png",
  "effects": []
}