{
  "_id": "45n492e4bxowkdqu",
  "name": "Vacuous Vessel",
  "permission": {
    "default": 0
  },
  "type": "spell",
  "data": {
    "description": {
      "value": "<div class=\"spell-description\">\n  <p>\n    <strong>School</strong>&nbsp;illusion&nbsp;(glamer);\n    <strong>Level</strong>&nbsp;bard 0, sorcerer/wizard 0;\n    \n    \n    \n    \n  </p>\n  <p>\n    <strong>Casting Time</strong>&nbsp;1 swift action<br>\n    <strong>Components</strong>&nbsp;V<br>\n  </p>\n  <p>\n    <strong>Range</strong>&nbsp;touch<br>\n    \n    <strong>Targets</strong>&nbsp;container touched<br>\n    \n    <strong>Duration</strong>&nbsp;1 round/level (D)<br>\n    <strong>Saving Throw</strong>&nbsp;Will negates; see text;&nbsp;<strong>Spell Resistance</strong>&nbsp;yes<br>\n  </p>\n  <h2>Description</h2>\n  <p>This spell makes a single bag, chest, sack, or other container look and feel empty. The container must be no larger than 1 cubic foot per caster level or the spell fails. Anyone peering into or reaching into the container must succeed at a Will save or perceive the container as being completely empty. All items within the container when the spell was cast are still present, but they can't be noticed unless removed from the bag-such as by someone who can perceive them, or who upends the container.  Casting <i>vacuous vessel</i> on another container or placing a new item in the existing container immediately dismisses the currently active spell.</p>\n</div>\n",
      "chat": "",
      "unidentified": ""
    },
    "tags": [],
    "activation": {
      "cost": 1,
      "type": "swift"
    },
    "unchainedAction": {
      "activation": {
        "cost": 1,
        "type": "action"
      }
    },
    "duration": {
      "value": null,
      "units": ""
    },
    "target": {
      "value": "container touched"
    },
    "range": {
      "value": null,
      "units": "touch",
      "maxIncrements": 1,
      "minValue": null,
      "minUnits": ""
    },
    "uses": {
      "value": 0,
      "max": 0,
      "per": "",
      "autoDeductCharges": true,
      "autoDeductChargesCost": "1"
    },
    "measureTemplate": {
      "type": "",
      "size": "0",
      "overrideColor": false,
      "customColor": "",
      "overrideTexture": false,
      "customTexture": ""
    },
    "attackName": "",
    "actionType": "spellsave",
    "attackBonus": "",
    "critConfirmBonus": "",
    "damage": {
      "parts": [],
      "critParts": [],
      "nonCritParts": []
    },
    "attackParts": [],
    "formulaicAttacks": {
      "count": {
        "formula": "",
        "value": null
      },
      "bonus": {
        "formula": ""
      },
      "label": null
    },
    "formula": "",
    "ability": {
      "attack": "",
      "damage": "",
      "damageMult": 1,
      "critRange": 20,
      "critMult": 2
    },
    "save": {
      "dc": "0",
      "type": "will",
      "description": "Will negates; see text"
    },
    "effectNotes": "",
    "attackNotes": "",
    "soundEffect": "",
    "links": {
      "children": []
    },
    "flags": {
      "boolean": [],
      "dictionary": []
    },
    "learnedAt": {
      "class": [
        [
          "sorcerer/wizard",
          0
        ],
        [
          "bard",
          0
        ]
      ],
      "domain": [],
      "subDomain": [],
      "elementalSchool": [],
      "bloodline": []
    },
    "level": 0,
    "clOffset": 0,
    "slOffset": 0,
    "school": "ill",
    "subschool": "glamer",
    "types": "",
    "nonlethal": false,
    "conditionals": [],
    "components": {
      "value": "",
      "verbal": true,
      "somatic": false,
      "material": false,
      "focus": false,
      "divineFocus": 0
    },
    "castTime": "",
    "materials": {
      "value": "",
      "focus": "",
      "gpValue": 0
    },
    "spellbook": "primary",
    "preparation": {
      "preparedAmount": 0,
      "maxAmount": 0,
      "autoDeductCharges": false,
      "spontaneousPrepared": true,
      "mode": "prepared"
    },
    "atWill": false,
    "sr": true,
    "shortDescription": "<p>This spell makes a single bag, chest, sack, or other container look and feel empty. The container must be no larger than 1 cubic foot per caster level or the spell fails. Anyone peering into or reaching into the container must succeed at a Will save or perceive the container as being completely empty. All items within the container when the spell was cast are still present, but they can't be noticed unless removed from the bag-such as by someone who can perceive them, or who upends the container.  Casting <i>vacuous vessel</i> on another container or placing a new item in the existing container immediately dismisses the currently active spell.</p>",
    "spellDuration": "1 round/level (D)",
    "spellEffect": "",
    "spellArea": "",
    "showInQuickbar": false,
    "spellPoints": {
      "cost": "1 + @sl"
    },
    "domain": false,
    "slotCost": 1
  },
  "flags": {},
  "img": "systems/pf1/icons/misc/magic-swirl.png",
  "effects": []
}